conduit/__init__.py
conduit/base.py
conduit/constants.py
conduit/exceptions.py
conduit/flow.py
conduit/meta.py
conduit/phasor.py
conduit/stream.py
conduit/units.py
conduit/version.py
conduit/transformers/__init__.py
conduit/transformers/conversions.py
conduit/transformers/decorators.py
conduit/transformers/phasor.py
tests/fixtures/__init__.py
tests/fixtures/streams.py
tests/test_transformers/__init__.py
tests/test_transformers/conftest.py
tests/test_transformers/test_conversions.py
tests/test_transformers/test_decorators.py
tests/test_transformers/test_phasor.py
conduit-1.1.dist-info/LICENSE.txt
conduit-1.1.dist-info/METADATA
conduit-1.1.dist-info/WHEEL
conduit-1.1.dist-info/entry_points.txt
conduit-1.1.dist-info/top_level.txt
conduit-1.1.dist-info/RECORD
