Metadata-Version: 2.1
Name: conduit
Version: 1.1
Summary: Python stream transformation package for common Power Engineering analytics.
Home-page: https://pingthings.io/
Author: Kevin D. Jones and PingThings, Inc.
Author-email: info@pingthings.io
Maintainer: Benjamin Bengfort
Maintainer-email: info@pingthings.io
License: Apache 2
Download-URL: https://github.com/PingThingsIO/conduit/tarball/v1.1
Project-URL: Documentation, https://pingthings.io/
Project-URL: Download, https://github.com/PingThingsIO/conduit/tarball/v1.1
Project-URL: Source, https://github.com/PingThingsIO/conduit
Project-URL: Tracker, https://github.com/PingThingsIO/conduit/issues
Keywords: power engineering,analytics,time series,data flow,transformers
Platform: UNKNOWN
Classifier: Development Status :: 3 - Alpha
Classifier: Intended Audience :: Developers
Classifier: Intended Audience :: Science/Research
Classifier: License :: OSI Approved :: BSD License
Classifier: Natural Language :: English
Classifier: Operating System :: OS Independent
Classifier: Programming Language :: Python
Classifier: Programming Language :: Python :: 3.6
Classifier: Programming Language :: Python :: 3.7
Classifier: Programming Language :: Python :: 3 :: Only
Classifier: Topic :: Scientific/Engineering
Classifier: Topic :: Software Development :: Libraries :: Python Modules
Requires-Python: >=3.6, <4
Requires-Dist: btrdb (>=5.4)
Requires-Dist: joblib (>=0.13.2)
Requires-Dist: numpy (>=1.16)
Requires-Dist: pandas (>=0.22)
Requires-Dist: scipy (>=1.2)
Requires-Dist: tabulate (>=0.8.3)
